odoo9_addon_product_tax_multicompany_default-9.0.1.0.0.99.dev5-py2.7-nspkg.pth
odoo9_addon_product_tax_multicompany_default-9.0.1.0.0.99.dev5.dist-info/METADATA
odoo9_addon_product_tax_multicompany_default-9.0.1.0.0.99.dev5.dist-info/RECORD
odoo9_addon_product_tax_multicompany_default-9.0.1.0.0.99.dev5.dist-info/WHEEL
odoo9_addon_product_tax_multicompany_default-9.0.1.0.0.99.dev5.dist-info/namespace_packages.txt
odoo9_addon_product_tax_multicompany_default-9.0.1.0.0.99.dev5.dist-info/top_level.txt
odoo_addons/product_tax_multicompany_default/README.rst
odoo_addons/product_tax_multicompany_default/__init__.py
odoo_addons/product_tax_multicompany_default/__openerp__.py
odoo_addons/product_tax_multicompany_default/i18n/de.po
odoo_addons/product_tax_multicompany_default/i18n/es.po
odoo_addons/product_tax_multicompany_default/i18n/fr.po
odoo_addons/product_tax_multicompany_default/i18n/product_tax_multicompany_default.pot
odoo_addons/product_tax_multicompany_default/models/__init__.py
odoo_addons/product_tax_multicompany_default/models/product.py
odoo_addons/product_tax_multicompany_default/static/description/icon.png
odoo_addons/product_tax_multicompany_default/tests/__init__.py
odoo_addons/product_tax_multicompany_default/tests/test_product_tax_multicompany.py
odoo_addons/product_tax_multicompany_default/views/product_template_view.xml
